<?xml version="1.0" encoding="UTF-8"?>
<results title="frequencies">
 <result title="frequency" count="20">Enterococcus faecalis</result>
 <result title="frequency" count="3">Cinnamomum albicans</result>
 <result title="frequency" count="3">Arctium lappa</result>
 <result title="frequency" count="2">Ferula gummosa</result>
 <result title="frequency" count="2">Ocimum sanctum</result>
 <result title="frequency" count="2">Aloe vera</result>
 <result title="frequency" count="2">Cinnamomum zeylanicum</result>
 <result title="frequency" count="1">O. sanctum</result>
 <result title="frequency" count="1">Morinda citrifolia</result>
 <result title="frequency" count="1">Z. multiflora</result>
 <result title="frequency" count="1">Mangifera indica</result>
 <result title="frequency" count="1">Glycolic propolis</result>
 <result title="frequency" count="1">S. aureus</result>
 <result title="frequency" count="1">Prevotella intermedia</result>
 <result title="frequency" count="1">Citrus aurantifolia</result>
 <result title="frequency" count="1">Terminalia chebula</result>
 <result title="frequency" count="1">Acacia nilotica</result>
 <result title="frequency" count="1">M. indica</result>
 <result title="frequency" count="1">Terminalia belerica</result>
</results>
