<?xml version="1.0" encoding="UTF-8"?>
<snippetsTree>
 <snippets file="ocimumten_xml/PMC5255966/results/search/plantparts/results.xml">
  <result pre="Wall. of the family Apocynaceae is also known as connessi" exact="bark" post="in English, kuṭaja in Sanskrit, kura or kurchi in"/>
  <result pre="English, kuṭaja in Sanskrit, kura or kurchi in Hindi. Its" exact="bark" post="and seeds have been used in the treatment of"/>
  <result pre="Association and American College of Cardiology) Renal or hepatic disease," exact="gall" post="stones, pancreatitis, diabetes mellitus, sepsis, infection, pneumonia Pregnant or"/>
  <result pre="activity against experimental amoebiasis in rats and hamsters,[ 20] The" exact="fruit" post="extract (50% ethanolic) showed antiprotozoal effect against Enta. histolytica"/>
  <result pre="the anti-inflammatory and analgesic activity of Cedrus deodara (Roxb.) Loud." exact="wood" post="oil J Ethnopharmacol 1999 65 21 7 10350366 7"/>
  <result pre="Vaid RM Gupta DK Three new steroidal alkaloids from the" exact="bark" post="of Holarrhena antidysenterica Phytochemistry 1988 27 925 28 11"/>
 </snippets>
</snippetsTree>
