<?xml version="1.0" encoding="UTF-8"?>
<results title="frequencies">
 <result title="frequency" word="nanoparticles" count="97"/>
 <result title="frequency" word="copper" count="95"/>
 <result title="frequency" word="Copper" count="70"/>
 <result title="frequency" word="synthesis" count="50"/>
 <result title="frequency" word="UV," count="45"/>
 <result title="frequency" word="Leaves" count="43"/>
 <result title="frequency" word="using" count="43"/>
 <result title="frequency" word="sulfate" count="37"/>
 <result title="frequency" word="FTIR," count="36"/>
 <result title="frequency" word="different" count="34"/>
 <result title="frequency" word="used" count="29"/>
 <result title="frequency" word="CuNPs" count="28"/>
 <result title="frequency" word="activity" count="27"/>
 <result title="frequency" word="plant" count="27"/>
 <result title="frequency" word="Antibacterial" count="25"/>
 <result title="frequency" word="Synthesis" count="24"/>
 <result title="frequency" word="extract" count="24"/>
 <result title="frequency" word="reduction" count="21"/>
 <result title="frequency" word="size" count="21"/>
 <result title="frequency" word="Spherical" count="20"/>
 <result title="frequency" word="Temp" count="20"/>
 <result title="frequency" word="reaction" count="20"/>
 <result title="frequency" word="{border-style" count="20"/>
 <result title="frequency" word="Green" count="19"/>
 <result title="frequency" word="SEM," count="19"/>
 <result title="frequency" word="XRD," count="19"/>
 <result title="frequency" word="Escherichia" count="18"/>
 <result title="frequency" word="Sci" count="18"/>
 <result title="frequency" word="px;}" count="18"/>
 <result title="frequency" word="#ffffff;}" count="17"/>
 <result title="frequency" word="Nanoparticles" count="17"/>
 <result title="frequency" word="Chem" count="15"/>
 <result title="frequency" word="TEM," count="15"/>
 <result title="frequency" word="antibacterial" count="15"/>
 <result title="frequency" word="antimicrobial" count="15"/>
 <result title="frequency" word="Fig." count="14"/>
 <result title="frequency" word="analysis" count="14"/>
 <result title="frequency" word="aqueous" count="14"/>
 <result title="frequency" word="Biosynthesis" count="13"/>
 <result title="frequency" word="NPs" count="13"/>
 <result title="frequency" word="characterization" count="13"/>
 <result title="frequency" word="metal" count="13"/>
 <result title="frequency" word="Catalytic" count="12"/>
 <result title="frequency" word="Int" count="12"/>
 <result title="frequency" word="X-ray" count="12"/>
 <result title="frequency" word="XRD" count="12"/>
 <result title="frequency" word="chemical" count="12"/>
 <result title="frequency" word="formation" count="12"/>
 <result title="frequency" word="green" count="12"/>
 <result title="frequency" word="ions" count="12"/>
 <result title="frequency" word="phytochemicals" count="12"/>
 <result title="frequency" word="Res" count="11"/>
 <result title="frequency" word="activity," count="11"/>
 <result title="frequency" word="coli" count="11"/>
 <result title="frequency" word="oxide" count="11"/>
 <result title="frequency" word="plants" count="11"/>
 <result title="frequency" word="properties" count="11"/>
 <result title="frequency" word="solution" count="11"/>
 <result title="frequency" word="(MTCC" count="10"/>
 <result title="frequency" word="Bacillus" count="10"/>
 <result title="frequency" word="concentration" count="10"/>
 <result title="frequency" word="form" count="10"/>
 <result title="frequency" word="spectroscopy" count="10"/>
 <result title="frequency" word="time" count="10"/>
 <result title="frequency" word="(ATCC" count="9"/>
 <result title="frequency" word="Kumar" count="9"/>
 <result title="frequency" word="Room" count="9"/>
 <result title="frequency" word="Staphylococcus" count="9"/>
 <result title="frequency" word="cell" count="9"/>
 <result title="frequency" word="chloride" count="9"/>
 <result title="frequency" word="electron" count="9"/>
 <result title="frequency" word="leaves" count="9"/>
 <result title="frequency" word="reducing" count="9"/>
 <result title="frequency" word="role" count="9"/>
 <result title="frequency" word="shown" count="9"/>
 <result title="frequency" word="°C," count="9"/>
 <result title="frequency" word="Citrus" count="8"/>
 <result title="frequency" word="CuNPs." count="8"/>
 <result title="frequency" word="EDX," count="8"/>
 <result title="frequency" word="Flavonoids" count="8"/>
 <result title="frequency" word="Fusarium" count="8"/>
 <result title="frequency" word="Hibiscus" count="8"/>
 <result title="frequency" word="Lett" count="8"/>
 <result title="frequency" word="Pharm" count="8"/>
 <result title="frequency" word="Pseudomonas" count="8"/>
 <result title="frequency" word="color" count="8"/>
 <result title="frequency" word="gold" count="8"/>
 <result title="frequency" word="high" count="8"/>
 <result title="frequency" word="methods" count="8"/>
 <result title="frequency" word="microscopy" count="8"/>
 <result title="frequency" word="min" count="8"/>
 <result title="frequency" word="px;" count="8"/>
 <result title="frequency" word="rosa-sinensis" count="8"/>
 <result title="frequency" word="silver" count="8"/>
 <result title="frequency" word="{font-family" count="8"/>
 <result title="frequency" word="-NP" count="7"/>
 <result title="frequency" word="-nitrophenol" count="7"/>
 <result title="frequency" word="Activity" count="7"/>
 <result title="frequency" word="COPPER" count="7"/>
 <result title="frequency" word="Colloid" count="7"/>
 <result title="frequency" word="NANOPARTICLES" count="7"/>
 <result title="frequency" word="Nano" count="7"/>
 <result title="frequency" word="SEM" count="7"/>
 <result title="frequency" word="TEM" count="7"/>
 <result title="frequency" word="Table" count="7"/>
 <result title="frequency" word="biosynthesis" count="7"/>
 <result title="frequency" word="coli," count="7"/>
 <result title="frequency" word="font-size" count="7"/>
 <result title="frequency" word="glycoside," count="7"/>
 <result title="frequency" word="groups" count="7"/>
 <result title="frequency" word="mechanism" count="7"/>
 <result title="frequency" word="nanoparticle" count="7"/>
 <result title="frequency" word="nuclei" count="7"/>
 <result title="frequency" word="oxysporum" count="7"/>
 <result title="frequency" word="shape" count="7"/>
 <result title="frequency" word="surface" count="7"/>
 <result title="frequency" word="synthesized" count="7"/>
 <result title="frequency" word="Calotropis" count="6"/>
 <result title="frequency" word="Characterization" count="6"/>
 <result title="frequency" word="Chen" count="6"/>
 <result title="frequency" word="CuNPs," count="6"/>
 <result title="frequency" word="Ginkgo" count="6"/>
 <result title="frequency" word="Khan" count="6"/>
 <result title="frequency" word="Leucas" count="6"/>
 <result title="frequency" word="Mater" count="6"/>
 <result title="frequency" word="Mechanism" count="6"/>
 <result title="frequency" word="Metal" count="6"/>
 <result title="frequency" word="Nanotechnol" count="6"/>
 <result title="frequency" word="Ocimum" count="6"/>
 <result title="frequency" word="Reduction" count="6"/>
 <result title="frequency" word="SAED" count="6"/>
 <result title="frequency" word="adsorption" count="6"/>
 <result title="frequency" word="applications" count="6"/>
 <result title="frequency" word="aureus" count="6"/>
 <result title="frequency" word="bacteria" count="6"/>
 <result title="frequency" word="biloba" count="6"/>
 <result title="frequency" word="double;" count="6"/>
 <result title="frequency" word="f.sp." count="6"/>
 <result title="frequency" word="ion" count="6"/>
 <result title="frequency" word="leaf" count="6"/>
 <result title="frequency" word="main" count="6"/>
 <result title="frequency" word="nanoparticles." count="6"/>
 <result title="frequency" word="physical" count="6"/>
 <result title="frequency" word="plants." count="6"/>
 <result title="frequency" word="present" count="6"/>
 <result title="frequency" word="review" count="6"/>
 <result title="frequency" word="sinensis" count="6"/>
 <result title="frequency" word="sodium" count="6"/>
 <result title="frequency" word="subtilis" count="6"/>
 <result title="frequency" word="&amp;lt; " count="5"/>
 <result title="frequency" word="Ahmad" count="5"/>
 <result title="frequency" word="Antifungal" count="5"/>
 <result title="frequency" word="Aspergillus" count="5"/>
 <result title="frequency" word="Camellia" count="5"/>
 <result title="frequency" word="Cassia" count="5"/>
 <result title="frequency" word="Curr" count="5"/>
 <result title="frequency" word="Datura" count="5"/>
 <result title="frequency" word="Dodonaea" count="5"/>
 <result title="frequency" word="Eucalyptus" count="5"/>
 <result title="frequency" word="Extract" count="5"/>
 <result title="frequency" word="FTIR" count="5"/>
 <result title="frequency" word="Flowers" count="5"/>
 <result title="frequency" word="NTA" count="5"/>
 <result title="frequency" word="Phyllanthus" count="5"/>
 <result title="frequency" word="Tannin," count="5"/>
 <result title="frequency" word="USING" count="5"/>
 <result title="frequency" word="Xanthomonas" count="5"/>
 <result title="frequency" word="Zhang" count="5"/>
 <result title="frequency" word="acetate" count="5"/>
 <result title="frequency" word="antifungal" count="5"/>
 <result title="frequency" word="antioxidant" count="5"/>
 <result title="frequency" word="biological" count="5"/>
 <result title="frequency" word="border-color" count="5"/>
 <result title="frequency" word="border-width" count="5"/>
 <result title="frequency" word="catalytic" count="5"/>
 <result title="frequency" word="changing" count="5"/>
 <result title="frequency" word="conditions" count="5"/>
 <result title="frequency" word="control" count="5"/>
 <result title="frequency" word="cytotoxicity" count="5"/>
 <result title="frequency" word="emblica" count="5"/>
 <result title="frequency" word="extract," count="5"/>
 <result title="frequency" word="flavonoid," count="5"/>
 <result title="frequency" word="flavonoids" count="5"/>
 <result title="frequency" word="low" count="5"/>
 <result title="frequency" word="marmelos" count="5"/>
 <result title="frequency" word="materials" count="5"/>
 <result title="frequency" word="measured" count="5"/>
 <result title="frequency" word="medicalinn" count="5"/>
 <result title="frequency" word="observed" count="5"/>
 <result title="frequency" word="peak" count="5"/>
 <result title="frequency" word="place" count="5"/>
 <result title="frequency" word="precursor" count="5"/>
 <result title="frequency" word="presence" count="5"/>
 <result title="frequency" word="procera" count="5"/>
 <result title="frequency" word="pv." count="5"/>
 <result title="frequency" word="reported" count="5"/>
 <result title="frequency" word="salt" count="5"/>
 <result title="frequency" word="salts" count="5"/>
 <result title="frequency" word="solid;" count="5"/>
 <result title="frequency" word="stabilizing" count="5"/>
 <result title="frequency" word="techniques" count="5"/>
 <result title="frequency" word="temp" count="5"/>
 <result title="frequency" word="temperature" count="5"/>
 <result title="frequency" word="terpenoids," count="5"/>
 <result title="frequency" word="viscosa" count="5"/>
 <result title="frequency" word="water" count="5"/>
 <result title="frequency" word="{font-style" count="5"/>
 <result title="frequency" word="{font-weight" count="5"/>
 <result title="frequency" word=":–." count="4"/>
 <result title="frequency" word="Aegle" count="4"/>
 <result title="frequency" word="Aloe" count="4"/>
 <result title="frequency" word="Appl" count="4"/>
 <result title="frequency" word="Asparagus" count="4"/>
 <result title="frequency" word="Biological" count="4"/>
 <result title="frequency" word="Capparis" count="4"/>
 <result title="frequency" word="Colletotrichum" count="4"/>
 <result title="frequency" word="Colocasia" count="4"/>
 <result title="frequency" word="Din" count="4"/>
 <result title="frequency" word="Effect" count="4"/>
 <result title="frequency" word="Euphorbia" count="4"/>
 <result title="frequency" word="Extracellular" count="4"/>
 <result title="frequency" word="FESEM," count="4"/>
 <result title="frequency" word="Fruit" count="4"/>
 <result title="frequency" word="Lee" count="4"/>
 <result title="frequency" word="Nanoscale" count="4"/>
 <result title="frequency" word="Nerium" count="4"/>
 <result title="frequency" word="PSA," count="4"/>
 <result title="frequency" word="Phytochemicals" count="4"/>
 <result title="frequency" word="Phytosynthesis" count="4"/>
 <result title="frequency" word="References" count="4"/>
 <result title="frequency" word="Rhizoctonia" count="4"/>
 <result title="frequency" word="SYNTHESIS" count="4"/>
 <result title="frequency" word="Salmonella" count="4"/>
 <result title="frequency" word="Sastry" count="4"/>
 <result title="frequency" word="Senapati" count="4"/>
 <result title="frequency" word="Sharma" count="4"/>
 <result title="frequency" word="Singh" count="4"/>
 <result title="frequency" word="Syzygium" count="4"/>
 <result title="frequency" word="Tridax" count="4"/>
 <result title="frequency" word="Turmeric" count="4"/>
 <result title="frequency" word="University" count="4"/>
 <result title="frequency" word="Using" count="4"/>
 <result title="frequency" word="Vitis" count="4"/>
 <result title="frequency" word="Zea" count="4"/>
 <result title="frequency" word="Zingiber" count="4"/>
 <result title="frequency" word="acid" count="4"/>
 <result title="frequency" word="aeruginosa" count="4"/>
 <result title="frequency" word="agents" count="4"/>
 <result title="frequency" word="alkaloid," count="4"/>
 <result title="frequency" word="applications." count="4"/>
 <result title="frequency" word="approach" count="4"/>
 <result title="frequency" word="aromaticum" count="4"/>
 <result title="frequency" word="article" count="4"/>
 <result title="frequency" word="assumed" count="4"/>
 <result title="frequency" word="axonopodis" count="4"/>
 <result title="frequency" word="bold" count="4"/>
 <result title="frequency" word="borohydride" count="4"/>
 <result title="frequency" word="carthami," count="4"/>
 <result title="frequency" word="case" count="4"/>
 <result title="frequency" word="chinensis" count="4"/>
 <result title="frequency" word="compounds" count="4"/>
 <result title="frequency" word="converted" count="4"/>
 <result title="frequency" word="courier;" count="4"/>
 <result title="frequency" word="curcumin" count="4"/>
 <result title="frequency" word="data" count="4"/>
 <result title="frequency" word="determined" count="4"/>
 <result title="frequency" word="diffraction" count="4"/>
 <result title="frequency" word="dried" count="4"/>
 <result title="frequency" word="em;" count="4"/>
 <result title="frequency" word="esculenta" count="4"/>
 <result title="frequency" word="esula" count="4"/>
 <result title="frequency" word="helped" count="4"/>
 <result title="frequency" word="industrial" count="4"/>
 <result title="frequency" word="interaction" count="4"/>
 <result title="frequency" word="literature" count="4"/>
 <result title="frequency" word="mays" count="4"/>
 <result title="frequency" word="mechanisms" count="4"/>
 <result title="frequency" word="medium" count="4"/>
 <result title="frequency" word="mixture" count="4"/>
 <result title="frequency" word="mixture." count="4"/>
 <result title="frequency" word="nanoparticles:" count="4"/>
 <result title="frequency" word="nitrate" count="4"/>
 <result title="frequency" word="officinale" count="4"/>
 <result title="frequency" word="oleander" count="4"/>
 <result title="frequency" word="phenolic" count="4"/>
 <result title="frequency" word="phenols" count="4"/>
 <result title="frequency" word="preparation" count="4"/>
 <result title="frequency" word="procumbens" count="4"/>
 <result title="frequency" word="pt;}" count="4"/>
 <result title="frequency" word="published" count="4"/>
 <result title="frequency" word="quercetin" count="4"/>
 <result title="frequency" word="room" count="4"/>
 <result title="frequency" word="sanctum" count="4"/>
 <result title="frequency" word="santin" count="4"/>
 <result title="frequency" word="sativum" count="4"/>
 <result title="frequency" word="screening" count="4"/>
 <result title="frequency" word="spherical" count="4"/>
 <result title="frequency" word="subtilis," count="4"/>
 <result title="frequency" word="synthesize" count="4"/>
 <result title="frequency" word="temp," count="4"/>
 <result title="frequency" word="use" count="4"/>
 <result title="frequency" word="value" count="4"/>
 <result title="frequency" word="vinifera" count="4"/>
 <result title="frequency" word="zeylanica" count="4"/>
</results>
