<?xml version="1.0" encoding="UTF-8"?>
<snippetsTree>
 <snippets file="osanctum200/PMC3831728/results/word/frequencies/results.xml">
  <result title="frequency" word="eugenol" count="40"/>
  <result title="frequency" word="essential" count="37"/>
  <result title="frequency" word="oil" count="32"/>
  <result title="frequency" word="gratissimum" count="30"/>
  <result title="frequency" word="activity" count="24"/>
  <result title="frequency" word="antioxidant" count="24"/>
  <result title="frequency" word="sanctum" count="23"/>
  <result title="frequency" word="methyl" count="22"/>
  <result title="frequency" word="oils" count="21"/>
 </snippets>
</snippetsTree>
