{
  "id": [
    "28686700"
  ],
  "source": [
    "MED"
  ],
  "pmid": [
    "28686700"
  ],
  "pmcid": [
    "PMC5501525"
  ],
  "doi": [
    "10.1371/journal.pone.0180414"
  ],
  "title": [
    "Rates of return to sorghum and millet research investments: A meta-analysis."
  ],
  "authorString": [
    "Zereyesus YA, Dalton TJ."
  ],
  "authorList": [
    {
      "author": [
        {
          "fullName": [
            "Zereyesus YA"
          ],
          "firstName": [
            "Yacob A"
          ],
          "lastName": [
            "Zereyesus"
          ],
          "initials": [
            "YA"
          ],
          "affiliation": [
            "Department of Agricultural Economics, Kansas State University, Manhattan, Kansas, United States of America."
          ]
        },
        {
          "fullName": [
            "Dalton TJ"
          ],
          "firstName": [
            "Timothy J"
          ],
          "lastName": [
            "Dalton"
          ],
          "initials": [
            "TJ"
          ],
          "authorId": [
            {
              "_": "0000-0003-0900-879X",
              "$": {
                "type": "ORCID"
              }
            }
          ],
          "affiliation": [
            "Department of Agricultural Economics, Kansas State University, Manhattan, Kansas, United States of America."
          ]
        }
      ]
    }
  ],
  "authorIdList": [
    {
      "authorId": [
        {
          "_": "0000-0003-0900-879X",
          "$": {
            "type": "ORCID"
          }
        }
      ]
    }
  ],
  "journalInfo": [
    {
      "issue": [
        "7"
      ],
      "volume": [
        "12"
      ],
      "journalIssueId": [
        "2572928"
      ],
      "dateOfPublication": [
        "2017 "
      ],
      "monthOfPublication": [
        "0"
      ],
      "yearOfPublication": [
        "2017"
      ],
      "printPublicationDate": [
        "2017-01-01"
      ],
      "journal": [
        {
          "title": [
            "PloS one"
          ],
          "ISOAbbreviation": [
            "PLoS ONE"
          ],
          "medlineAbbreviation": [
            "PLoS One"
          ],
          "NLMid": [
            "101285081"
          ],
          "ISSN": [
            "1932-6203"
          ],
          "ESSN": [
            "1932-6203"
          ]
        }
      ]
    }
  ],
  "pubYear": [
    "2017"
  ],
  "pageInfo": [
    "e0180414"
  ],
  "abstractText": [
    "Sorghum and millet grow in some of the most heterogeneous and austere agroecologies around the world. These crops are amongst the top five cereal sources of food and feed. Yet, few studies document the impact of sorghum and millet genetic enhancement. The Internal Rate of Return (ROR) is one of the most popular metrics used to measure the economic return on investment on agricultural research and development (R&D). This study conducted a meta-analysis of 59 sorghum and millet ROR estimates obtained from 25 sources published between 1958 and 2015. The average rate of return to sorghum and millet R&D investment is between 54-76 percent per year. All studies computed social rather than private RORs because the technologies were developed using public funds originating from host country National Agricultural Research Systems (NARS) and international organizations such as the INTSORMIL CRSP, ICRISAT and others. Nearly three quarter of the studies focused only on sorghum (72 percent) and around one tenth of the studies (8 percent) on millet. Regression models analyzed the determinants of variation in the reported RORs. Results show that ex-ante type and self-evaluated type of analyses are positively and significantly associated with the ROR estimates. Compared to estimates conducted by a university, results from international institutions and other mixed organizations provided significantly smaller estimates. Estimates conducted at national level also are significantly lower than those conducted at sub-national levels. The ROR is higher for studies conducted in the United States and for those conducted more recently. The study also reconstructed modified internal rate of return (MIRR) for a sub-sample of the reported RORs following recent methods from the literature. These results show that the MIRR estimates are significantly smaller than the reported ROR estimates. Both results indicate that investment in sorghum and millet research generates high social rates of return."
  ],
  "affiliation": [
    "Department of Agricultural Economics, Kansas State University, Manhattan, Kansas, United States of America."
  ],
  "language": [
    "eng"
  ],
  "pubModel": [
    "Electronic-eCollection"
  ],
  "pubTypeList": [
    {
      "pubType": [
        "Meta-Analysis",
        "research-article",
        "Journal Article"
      ]
    }
  ],
  "meshHeadingList": [
    {
      "meshHeading": [
        {
          "majorTopic_YN": [
            "N"
          ],
          "descriptorName": [
            "Humans"
          ]
        },
        {
          "majorTopic_YN": [
            "N"
          ],
          "descriptorName": [
            "Sorghum"
          ],
          "meshQualifierList": [
            {
              "meshQualifier": [
                {
                  "abbreviation": [
                    "GE"
                  ],
                  "qualifierName": [
                    "genetics"
                  ],
                  "majorTopic_YN": [
                    "Y"
                  ]
                },
                {
                  "abbreviation": [
                    "GD"
                  ],
                  "qualifierName": [
                    "growth & development"
                  ],
                  "majorTopic_YN": [
                    "N"
                  ]
                }
              ]
            }
          ]
        },
        {
          "majorTopic_YN": [
            "N"
          ],
          "descriptorName": [
            "Crops, Agricultural"
          ],
          "meshQualifierList": [
            {
              "meshQualifier": [
                {
                  "abbreviation": [
                    "EC"
                  ],
                  "qualifierName": [
                    "economics"
                  ],
                  "majorTopic_YN": [
                    "Y"
                  ]
                }
              ]
            }
          ]
        },
        {
          "majorTopic_YN": [
            "N"
          ],
          "descriptorName": [
            "Regression Analysis"
          ]
        },
        {
          "majorTopic_YN": [
            "N"
          ],
          "descriptorName": [
            "Genetic Research"
          ],
          "meshQualifierList": [
            {
              "meshQualifier": [
                {
                  "abbreviation": [
                    "EC"
                  ],
                  "qualifierName": [
                    "economics"
                  ],
                  "majorTopic_YN": [
                    "Y"
                  ]
                }
              ]
            }
          ]
        },
        {
          "majorTopic_YN": [
            "Y"
          ],
          "descriptorName": [
            "Cost-Benefit Analysis"
          ]
        },
        {
          "majorTopic_YN": [
            "N"
          ],
          "descriptorName": [
            "Investments"
          ],
          "meshQualifierList": [
            {
              "meshQualifier": [
                {
                  "abbreviation": [
                    "SN"
                  ],
                  "qualifierName": [
                    "statistics & numerical data"
                  ],
                  "majorTopic_YN": [
                    "N"
                  ]
                }
              ]
            }
          ]
        },
        {
          "majorTopic_YN": [
            "N"
          ],
          "descriptorName": [
            "Edible Grain"
          ],
          "meshQualifierList": [
            {
              "meshQualifier": [
                {
                  "abbreviation": [
                    "EC"
                  ],
                  "qualifierName": [
                    "economics"
                  ],
                  "majorTopic_YN": [
                    "N"
                  ]
                },
                {
                  "abbreviation": [
                    "GE"
                  ],
                  "qualifierName": [
                    "genetics"
                  ],
                  "majorTopic_YN": [
                    "N"
                  ]
                },
                {
                  "abbreviation": [
                    "GD"
                  ],
                  "qualifierName": [
                    "growth & development"
                  ],
                  "majorTopic_YN": [
                    "N"
                  ]
                }
              ]
            }
          ]
        },
        {
          "majorTopic_YN": [
            "N"
          ],
          "descriptorName": [
            "Plant Breeding"
          ],
          "meshQualifierList": [
            {
              "meshQualifier": [
                {
                  "abbreviation": [
                    "EC"
                  ],
                  "qualifierName": [
                    "economics"
                  ],
                  "majorTopic_YN": [
                    "Y"
                  ]
                }
              ]
            }
          ]
        },
        {
          "majorTopic_YN": [
            "N"
          ],
          "descriptorName": [
            "Millets"
          ],
          "meshQualifierList": [
            {
              "meshQualifier": [
                {
                  "abbreviation": [
                    "GE"
                  ],
                  "qualifierName": [
                    "genetics"
                  ],
                  "majorTopic_YN": [
                    "Y"
                  ]
                },
                {
                  "abbreviation": [
                    "GD"
                  ],
                  "qualifierName": [
                    "growth & development"
                  ],
                  "majorTopic_YN": [
                    "N"
                  ]
                }
              ]
            }
          ]
        }
      ]
    }
  ],
  "subsetList": [
    {
      "subset": [
        {
          "code": [
            "IM"
          ],
          "name": [
            "Index Medicus"
          ]
        }
      ]
    }
  ],
  "fullTextUrlList": [
    {
      "fullTextUrl": [
        {
          "availability": [
            "Open access"
          ],
          "availabilityCode": [
            "OA"
          ],
          "documentStyle": [
            "pdf"
          ],
          "site": [
            "Europe_PMC"
          ],
          "url": [
            "http://europepmc.org/articles/PMC5501525?pdf=render"
          ]
        },
        {
          "availability": [
            "Open access"
          ],
          "availabilityCode": [
            "OA"
          ],
          "documentStyle": [
            "html"
          ],
          "site": [
            "Europe_PMC"
          ],
          "url": [
            "http://europepmc.org/articles/PMC5501525"
          ]
        },
        {
          "availability": [
            "Subscription required"
          ],
          "availabilityCode": [
            "S"
          ],
          "documentStyle": [
            "doi"
          ],
          "site": [
            "DOI"
          ],
          "url": [
            "https://doi.org/10.1371/journal.pone.0180414"
          ]
        }
      ]
    }
  ],
  "isOpenAccess": [
    "Y"
  ],
  "inEPMC": [
    "Y"
  ],
  "inPMC": [
    "N"
  ],
  "hasPDF": [
    "Y"
  ],
  "hasBook": [
    "N"
  ],
  "hasSuppl": [
    "Y"
  ],
  "citedByCount": [
    "0"
  ],
  "hasReferences": [
    "Y"
  ],
  "hasTextMinedTerms": [
    "Y"
  ],
  "hasDbCrossReferences": [
    "N"
  ],
  "hasLabsLinks": [
    "Y"
  ],
  "license": [
    "cc by"
  ],
  "authMan": [
    "N"
  ],
  "epmcAuthMan": [
    "N"
  ],
  "nihAuthMan": [
    "N"
  ],
  "hasTMAccessionNumbers": [
    "N"
  ],
  "dateOfCompletion": [
    "2017-09-27"
  ],
  "dateOfCreation": [
    "2017-07-07"
  ],
  "dateOfRevision": [
    "2017-09-27"
  ],
  "electronicPublicationDate": [
    "2017-07-07"
  ],
  "firstPublicationDate": [
    "2017-07-07"
  ]
}