{
  "id": [
    "29848962"
  ],
  "source": [
    "MED"
  ],
  "pmid": [
    "29848962"
  ],
  "pmcid": [
    "PMC6024783"
  ],
  "doi": [
    "10.3390/nu10060694"
  ],
  "title": [
    "Postprandial Glycaemic Responses of Dried Fruit-Containing Meals in Healthy Adults: Results from a Randomised Trial."
  ],
  "authorString": [
    "Zhu R, Fan Z, Dong Y, Liu M, Wang L, Pan H."
  ],
  "authorList": [
    {
      "author": [
        {
          "fullName": [
            "Zhu R"
          ],
          "firstName": [
            "Ruixin"
          ],
          "lastName": [
            "Zhu"
          ],
          "initials": [
            "R"
          ],
          "affiliation": [
            "Beijing Advanced Innovation Centre for Food Nutrition and Human Health, China Agricultural University, Beijing 100083, China. zhuruixin07@126.com."
          ]
        },
        {
          "fullName": [
            "Fan Z"
          ],
          "firstName": [
            "Zhihong"
          ],
          "lastName": [
            "Fan"
          ],
          "initials": [
            "Z"
          ],
          "affiliation": [
            "Beijing Advanced Innovation Centre for Food Nutrition and Human Health, China Agricultural University, Beijing 100083, China. daisyfan@cau.edu.cn."
          ]
        },
        {
          "fullName": [
            "Dong Y"
          ],
          "firstName": [
            "Yang"
          ],
          "lastName": [
            "Dong"
          ],
          "initials": [
            "Y"
          ],
          "affiliation": [
            "Beijing Advanced Innovation Centre for Food Nutrition and Human Health, China Agricultural University, Beijing 100083, China. feidi@sina.com."
          ]
        },
        {
          "fullName": [
            "Liu M"
          ],
          "firstName": [
            "Manman"
          ],
          "lastName": [
            "Liu"
          ],
          "initials": [
            "M"
          ],
          "affiliation": [
            "Department of Food Science and Engineering, College of Biological Science and Technology, Beijing Forestry University, Beijing 100083, China. manman_Liu@bjfu.edu.cn."
          ]
        },
        {
          "fullName": [
            "Wang L"
          ],
          "firstName": [
            "Linlin"
          ],
          "lastName": [
            "Wang"
          ],
          "initials": [
            "L"
          ],
          "affiliation": [
            "Beijing Advanced Innovation Centre for Food Nutrition and Human Health, China Agricultural University, Beijing 100083, China. lynn9523@126.com."
          ]
        },
        {
          "fullName": [
            "Pan H"
          ],
          "firstName": [
            "Haikun"
          ],
          "lastName": [
            "Pan"
          ],
          "initials": [
            "H"
          ],
          "affiliation": [
            "Beijing Advanced Innovation Centre for Food Nutrition and Human Health, China Agricultural University, Beijing 100083, China. m15201424460_3@163.com."
          ]
        }
      ]
    }
  ],
  "journalInfo": [
    {
      "issue": [
        "6"
      ],
      "volume": [
        "10"
      ],
      "journalIssueId": [
        "2686513"
      ],
      "dateOfPublication": [
        "2018 May"
      ],
      "monthOfPublication": [
        "5"
      ],
      "yearOfPublication": [
        "2018"
      ],
      "printPublicationDate": [
        "2018-05-01"
      ],
      "journal": [
        {
          "title": [
            "Nutrients"
          ],
          "ISOAbbreviation": [
            "Nutrients"
          ],
          "medlineAbbreviation": [
            "Nutrients"
          ],
          "NLMid": [
            "101521595"
          ],
          "ISSN": [
            "2072-6643"
          ],
          "ESSN": [
            "2072-6643"
          ]
        }
      ]
    }
  ],
  "pubYear": [
    "2018"
  ],
  "abstractText": [
    "The aim of this study was to explore the glycaemic response (GR) patterns of four dried fruits (DF) and the mixed meals containing dried fruits, rice and almonds. Dried apples (DApp), dried jujubes (DJ), raisins (Ra) and dried apricots (DApr) were tested in eleven healthy subjects in random order. Test meals included the following 3 groups: (1) dried fruits containing 50 g available carbohydrates; (2) mixed meals consisting of DF and rice (DF + R), each contributing 25 g available carbohydrates; (3) Group (2) supplemented with 30 g almonds (DF + R + A). The postprandial GR and other characteristics in 240 min were investigated. The GI values of 4 DFs were 43 for DApp, 55 for DJ, 56 for both Ra and DApr. The DApp displayed the smallest amplitude of glycaemic excursion within 240 min (MAGE0⁻240). Compared with rice, the DApp + R meal elicited a significantly reduced GR and a smaller MAGE0⁻240 (GI 81 vs. 65). With the addition of almonds, the GIs and MAGE0⁻240 decreased significantly in all DF + A + R combinations except DApp + R + A. The ratio of total fructose/glucose contents of test meals were negatively correlated to GIs. Dried fruits and nuts may have the potential to mitigate the postprandial GR when jointly introduced into glycaemic management diets."
  ],
  "affiliation": [
    "Beijing Advanced Innovation Centre for Food Nutrition and Human Health, China Agricultural University, Beijing 100083, China. zhuruixin07@126.com."
  ],
  "language": [
    "eng"
  ],
  "pubModel": [
    "Electronic"
  ],
  "pubTypeList": [
    {
      "pubType": [
        "Comparative Study",
        "research-article",
        "Randomized Controlled Trial",
        "Journal Article"
      ]
    }
  ],
  "meshHeadingList": [
    {
      "meshHeading": [
        {
          "majorTopic_YN": [
            "N"
          ],
          "descriptorName": [
            "Humans"
          ]
        },
        {
          "majorTopic_YN": [
            "N"
          ],
          "descriptorName": [
            "Ziziphus"
          ]
        },
        {
          "majorTopic_YN": [
            "N"
          ],
          "descriptorName": [
            "Malus"
          ]
        },
        {
          "majorTopic_YN": [
            "N"
          ],
          "descriptorName": [
            "Vitis"
          ]
        },
        {
          "majorTopic_YN": [
            "Y"
          ],
          "descriptorName": [
            "Fruit"
          ]
        },
        {
          "majorTopic_YN": [
            "N"
          ],
          "descriptorName": [
            "Nuts"
          ]
        },
        {
          "majorTopic_YN": [
            "N"
          ],
          "descriptorName": [
            "Seeds"
          ]
        },
        {
          "majorTopic_YN": [
            "N"
          ],
          "descriptorName": [
            "Cross-Over Studies"
          ]
        },
        {
          "majorTopic_YN": [
            "Y"
          ],
          "descriptorName": [
            "Glycemic Index"
          ]
        },
        {
          "majorTopic_YN": [
            "N"
          ],
          "descriptorName": [
            "Postprandial Period"
          ]
        },
        {
          "majorTopic_YN": [
            "N"
          ],
          "descriptorName": [
            "Food Handling"
          ]
        },
        {
          "majorTopic_YN": [
            "N"
          ],
          "descriptorName": [
            "Adolescent"
          ]
        },
        {
          "majorTopic_YN": [
            "N"
          ],
          "descriptorName": [
            "Adult"
          ]
        },
        {
          "majorTopic_YN": [
            "N"
          ],
          "descriptorName": [
            "Female"
          ]
        },
        {
          "majorTopic_YN": [
            "N"
          ],
          "descriptorName": [
            "Male"
          ]
        },
        {
          "majorTopic_YN": [
            "N"
          ],
          "descriptorName": [
            "Young Adult"
          ]
        },
        {
          "majorTopic_YN": [
            "Y"
          ],
          "descriptorName": [
            "Food, Preserved"
          ]
        },
        {
          "majorTopic_YN": [
            "Y"
          ],
          "descriptorName": [
            "Meals"
          ]
        },
        {
          "majorTopic_YN": [
            "N"
          ],
          "descriptorName": [
            "Snacks"
          ]
        },
        {
          "majorTopic_YN": [
            "N"
          ],
          "descriptorName": [
            "Oryza"
          ]
        },
        {
          "majorTopic_YN": [
            "N"
          ],
          "descriptorName": [
            "Prunus dulcis"
          ]
        },
        {
          "majorTopic_YN": [
            "N"
          ],
          "descriptorName": [
            "Prunus armeniaca"
          ]
        }
      ]
    }
  ],
  "keywordList": [
    {
      "keyword": [
        "Almonds",
        "Mixed Diets",
        "Dried Fruits",
        "Glycaemic Responses",
        "Dried Jujubes"
      ]
    }
  ],
  "subsetList": [
    {
      "subset": [
        {
          "code": [
            "IM"
          ],
          "name": [
            "Index Medicus"
          ]
        }
      ]
    }
  ],
  "fullTextUrlList": [
    {
      "fullTextUrl": [
        {
          "availability": [
            "Open access"
          ],
          "availabilityCode": [
            "OA"
          ],
          "documentStyle": [
            "pdf"
          ],
          "site": [
            "Europe_PMC"
          ],
          "url": [
            "http://europepmc.org/articles/PMC6024783?pdf=render"
          ]
        },
        {
          "availability": [
            "Open access"
          ],
          "availabilityCode": [
            "OA"
          ],
          "documentStyle": [
            "html"
          ],
          "site": [
            "Europe_PMC"
          ],
          "url": [
            "http://europepmc.org/articles/PMC6024783"
          ]
        },
        {
          "availability": [
            "Subscription required"
          ],
          "availabilityCode": [
            "S"
          ],
          "documentStyle": [
            "doi"
          ],
          "site": [
            "DOI"
          ],
          "url": [
            "https://doi.org/10.3390/nu10060694"
          ]
        }
      ]
    }
  ],
  "isOpenAccess": [
    "Y"
  ],
  "inEPMC": [
    "Y"
  ],
  "inPMC": [
    "N"
  ],
  "hasPDF": [
    "Y"
  ],
  "hasBook": [
    "N"
  ],
  "hasSuppl": [
    "N"
  ],
  "citedByCount": [
    "0"
  ],
  "hasReferences": [
    "Y"
  ],
  "hasTextMinedTerms": [
    "Y"
  ],
  "hasDbCrossReferences": [
    "N"
  ],
  "hasLabsLinks": [
    "Y"
  ],
  "license": [
    "cc by"
  ],
  "authMan": [
    "N"
  ],
  "epmcAuthMan": [
    "N"
  ],
  "nihAuthMan": [
    "N"
  ],
  "hasTMAccessionNumbers": [
    "N"
  ],
  "dateOfCompletion": [
    "2018-10-15"
  ],
  "dateOfCreation": [
    "2018-06-01"
  ],
  "dateOfRevision": [
    "2018-10-15"
  ],
  "electronicPublicationDate": [
    "2018-05-30"
  ],
  "firstPublicationDate": [
    "2018-05-30"
  ]
}