<?xml version="1.0" encoding="UTF-8"?>
<results title="frequencies">
 <result title="frequency" word="silver" count="73"/>
 <result title="frequency" word="nanoparticles" count="70"/>
 <result title="frequency" word=". × " count="64"/>
 <result title="frequency" word="leaf" count="52"/>
 <result title="frequency" word="sanctum" count="51"/>
 <result title="frequency" word="extract" count="38"/>
 <result title="frequency" word="plant" count="32"/>
 <result title="frequency" word="aqueous" count="30"/>
 <result title="frequency" word="using" count="24"/>
 <result title="frequency" word="extracts" count="22"/>
 <result title="frequency" word="Ocimum" count="21"/>
 <result title="frequency" word="synthesis" count="21"/>
 <result title="frequency" word="{border-style" count="20"/>
 <result title="frequency" word="AgNPs" count="18"/>
 <result title="frequency" word="formed" count="18"/>
 <result title="frequency" word="px;}" count="18"/>
 <result title="frequency" word="#ffffff;}" count="17"/>
 <result title="frequency" word="],[" count="17"/>
 <result title="frequency" word="bacteria" count="16"/>
 <result title="frequency" word="different" count="16"/>
 <result title="frequency" word="activity" count="13"/>
 <result title="frequency" word="antibacterial" count="12"/>
 <result title="frequency" word="concentrations" count="11"/>
 <result title="frequency" word="solution" count="11"/>
 <result title="frequency" word="AgNO" count="10"/>
 <result title="frequency" word="original" count="10"/>
 <result title="frequency" word="sunlight" count="10"/>
 <result title="frequency" word="Gram-positive" count="9"/>
 <result title="frequency" word="concentration" count="9"/>
 <result title="frequency" word="medicinal" count="9"/>
 <result title="frequency" word="used" count="9"/>
 <result title="frequency" word="Authors’" count="8"/>
 <result title="frequency" word="Figure" count="8"/>
 <result title="frequency" word="Gram-negative" count="8"/>
 <result title="frequency" word="UV-vis" count="8"/>
 <result title="frequency" word="biogenic" count="8"/>
 <result title="frequency" word="chemical" count="8"/>
 <result title="frequency" word="fresh" count="8"/>
 <result title="frequency" word="growth" count="8"/>
 <result title="frequency" word="metal" count="8"/>
 <result title="frequency" word="px;" count="8"/>
 <result title="frequency" word="rapid" count="8"/>
 <result title="frequency" word="synthesized" count="8"/>
 <result title="frequency" word="time" count="8"/>
 <result title="frequency" word="{font-family" count="8"/>
 <result title="frequency" word="(%," count="7"/>
 <result title="frequency" word="LINK" count="7"/>
 <result title="frequency" word="Linn." count="7"/>
 <result title="frequency" word="PLE" count="7"/>
 <result title="frequency" word="Staphylococcus" count="7"/>
 <result title="frequency" word="Synthesis" count="7"/>
 <result title="frequency" word="absorption" count="7"/>
 <result title="frequency" word="action" count="7"/>
 <result title="frequency" word="aureus" count="7"/>
 <result title="frequency" word="direct" count="7"/>
 <result title="frequency" word="figure" count="7"/>
 <result title="frequency" word="file" count="7"/>
 <result title="frequency" word="font-size" count="7"/>
 <result title="frequency" word="measured" count="7"/>
 <result title="frequency" word="nano" count="7"/>
 <result title="frequency" word="pathogenic" count="7"/>
 <result title="frequency" word="treatment" count="7"/>
 <result title="frequency" word="./s---" count="6"/>
 <result title="frequency" word="Antimicrobial" count="6"/>
 <result title="frequency" word="Chem" count="6"/>
 <result title="frequency" word="Res" count="6"/>
 <result title="frequency" word="TEM" count="6"/>
 <result title="frequency" word="activities" count="6"/>
 <result title="frequency" word="antimicrobial" count="6"/>
 <result title="frequency" word="bacterial" count="6"/>
 <result title="frequency" word="double;" count="6"/>
 <result title="frequency" word="formation" count="6"/>
 <result title="frequency" word="leaves" count="6"/>
 <result title="frequency" word="metallic" count="6"/>
 <result title="frequency" word="method" count="6"/>
 <result title="frequency" word="nanoparticles." count="6"/>
 <result title="frequency" word="nitrate" count="6"/>
 <result title="frequency" word="observed" count="6"/>
 <result title="frequency" word="properties" count="6"/>
 <result title="frequency" word="size" count="6"/>
 <result title="frequency" word="spectra" count="6"/>
 <result title="frequency" word="(Figure" count="5"/>
 <result title="frequency" word="CFU" count="5"/>
 <result title="frequency" word="Sci" count="5"/>
 <result title="frequency" word="UV-visible" count="5"/>
 <result title="frequency" word="adhatoda" count="5"/>
 <result title="frequency" word="applications" count="5"/>
 <result title="frequency" word="available" count="5"/>
 <result title="frequency" word="biomedical" count="5"/>
 <result title="frequency" word="border-color" count="5"/>
 <result title="frequency" word="border-width" count="5"/>
 <result title="frequency" word="color" count="5"/>
 <result title="frequency" word="cultures" count="5"/>
 <result title="frequency" word="enhanced" count="5"/>
 <result title="frequency" word="inhibitory" count="5"/>
 <result title="frequency" word="ions" count="5"/>
 <result title="frequency" word="min" count="5"/>
 <result title="frequency" word="mode" count="5"/>
 <result title="frequency" word="nanoparticles," count="5"/>
 <result title="frequency" word="plants" count="5"/>
 <result title="frequency" word="reducing" count="5"/>
 <result title="frequency" word="solid;" count="5"/>
 <result title="frequency" word="surface" count="5"/>
 <result title="frequency" word="various" count="5"/>
 <result title="frequency" word="varying" count="5"/>
 <result title="frequency" word="{font-style" count="5"/>
 <result title="frequency" word="{font-weight" count="5"/>
 <result title="frequency" word=" × " count="5"/>
 <result title="frequency" word="(PLE)" count="4"/>
 <result title="frequency" word="(dispersed" count="4"/>
 <result title="frequency" word="Adv" count="4"/>
 <result title="frequency" word="Bacillus" count="4"/>
 <result title="frequency" word="Chen" count="4"/>
 <result title="frequency" word="Linn" count="4"/>
 <result title="frequency" word="MTCC" count="4"/>
 <result title="frequency" word="MTCC," count="4"/>
 <result title="frequency" word="Pseudomonas" count="4"/>
 <result title="frequency" word="Silver" count="4"/>
 <result title="frequency" word="Tulsi" count="4"/>
 <result title="frequency" word="aeruginosa" count="4"/>
 <result title="frequency" word="applying" count="4"/>
 <result title="frequency" word="article" count="4"/>
 <result title="frequency" word="bactericidal" count="4"/>
 <result title="frequency" word="band" count="4"/>
 <result title="frequency" word="bioreduction" count="4"/>
 <result title="frequency" word="biosynthesis" count="4"/>
 <result title="frequency" word="bold" count="4"/>
 <result title="frequency" word="capping" count="4"/>
 <result title="frequency" word="compounds" count="4"/>
 <result title="frequency" word="courier;" count="4"/>
 <result title="frequency" word="efficacy" count="4"/>
 <result title="frequency" word="efficient" count="4"/>
 <result title="frequency" word="electron" count="4"/>
 <result title="frequency" word="em;" count="4"/>
 <result title="frequency" word="experimental" count="4"/>
 <result title="frequency" word="followed" count="4"/>
 <result title="frequency" word="gold" count="4"/>
 <result title="frequency" word="human" count="4"/>
 <result title="frequency" word="influence" count="4"/>
 <result title="frequency" word="limon" count="4"/>
 <result title="frequency" word="min." count="4"/>
 <result title="frequency" word="plasmon" count="4"/>
 <result title="frequency" word="produced" count="4"/>
 <result title="frequency" word="pt;}" count="4"/>
 <result title="frequency" word="range" count="4"/>
 <result title="frequency" word="reported" count="4"/>
 <result title="frequency" word="results" count="4"/>
 <result title="frequency" word="showed" count="4"/>
 <result title="frequency" word="stabilization" count="4"/>
 <result title="frequency" word="strains" count="4"/>
 <result title="frequency" word="studied" count="4"/>
 <result title="frequency" word="studies" count="4"/>
 <result title="frequency" word="study" count="4"/>
 <result title="frequency" word="use" count="4"/>
</results>
